dessinemoi/__init__.py
dessinemoi/_core.py
dessinemoi/_version.py
dessinemoi-25.1.0.dist-info/METADATA
dessinemoi-25.1.0.dist-info/WHEEL
dessinemoi-25.1.0.dist-info/licenses/LICENSE
dessinemoi-25.1.0.dist-info/RECORD
