Metadata-Version: 2.4
Name: dessinemoi
Version: 25.1.0
Summary: A simple factory implementation written in Python
Project-URL: Changelog, https://github.com/rayference/dessinemoi/blob/main/CHANGELOG.md
Project-URL: Documentation, https://dessinemoi.readthedocs.io
Project-URL: Homepage, https://github.com/rayference/dessinemoi
Project-URL: Issues, https://github.com/rayference/dessinemoi/issues
Project-URL: Repository, https://github.com/rayference/dessinemoi
Author-email: Vincent Leroy <vincent.leroy@rayference.eu>
License: MIT
License-File: LICENSE
Classifier: Development Status :: 6 - Mature
Classifier: License :: OSI Approved :: MIT License
Classifier: Programming Language :: Python :: 3.8
Classifier: Programming Language :: Python :: 3.9
Classifier: Programming Language :: Python :: 3.10
Classifier: Programming Language :: Python :: 3.11
Classifier: Programming Language :: Python :: 3.12
Classifier: Programming Language :: Python :: 3.13
Requires-Python: >=3.8
Requires-Dist: attrs>=21
